src/__init__.py
src/__main__.py
serializers_set-1.0.dist-info/METADATA
serializers_set-1.0.dist-info/WHEEL
serializers_set-1.0.dist-info/top_level.txt
serializers_set-1.0.dist-info/RECORD
