Metadata-Version: 2.1
Name: serializers-set
Version: 1.0
Summary: json, toml, yaml serializers
Author: sakovnv
Author-email: sakovnv@gmail.com
License: UNKNOWN
Keywords: json toml yaml serializer
Platform: UNKNOWN
